[
 {
  "android": "9.0",
  "codename": "beryllium",
  "device": "Poco F1 Global",
  "download": "http://bigota.d.miui.com/9.2.21/beryllium_global_images_9.2.21_20190221.0000.00_9.0_global_c41a39d966.tgz",
  "filename": "beryllium_global_images_9.2.21_20190221.0000.00_9.0_global_c41a39d966.tgz",
  "filesize": "2.5G",
  "md5": "c41a39d9661c9dee33b505c6567cfc5a",
  "version": "9.2.21"
 },
 {
  "android": "8.1",
  "codename": "cactus",
  "device": "Redmi 6A China",
  "download": "http://bigota.d.miui.com/9.2.21/cactus_images_9.2.21_20190221.0000.00_8.1_cn_faaf14e8cf.tgz",
  "filename": "cactus_images_9.2.21_20190221.0000.00_8.1_cn_faaf14e8cf.tgz",
  "filesize": "1.9G",
  "md5": "faaf14e8cfa064c4644e777c95bbb1ab",
  "version": "9.2.21"
 },
 {
  "android": "8.1",
  "codename": "cactus",
  "device": "Redmi 6A Global",
  "download": "http://bigota.d.miui.com/9.2.21/cactus_global_images_9.2.21_20190221.0000.00_8.1_global_cee1fa0418.tgz",
  "filename": "cactus_global_images_9.2.21_20190221.0000.00_8.1_global_cee1fa0418.tgz",
  "filesize": "1.8G",
  "md5": "cee1fa0418b5255de185d3d114497d3d",
  "version": "9.2.21"
 },
 {
  "android": "7.0",
  "codename": "cappu",
  "device": "Mi Pad 3 China",
  "download": "http://bigota.d.miui.com/9.2.28/cappu_images_9.2.28_20190228.0000.00_7.0_cn_848d0cc2fc.tgz",
  "filename": "cappu_images_9.2.28_20190228.0000.00_7.0_cn_848d0cc2fc.tgz",
  "filesize": "1.1G",
  "md5": "848d0cc2fc923021011779f6a28e8948",
  "version": "9.2.28"
 },
 {
  "android": "8.0",
  "codename": "capricorn",
  "device": "Mi 5s China",
  "download": "http://bigota.d.miui.com/9.2.28/capricorn_images_9.2.28_20190228.0000.00_8.0_cn_5d301ec55c.tgz",
  "filename": "capricorn_images_9.2.28_20190228.0000.00_8.0_cn_5d301ec55c.tgz",
  "filesize": "1.8G",
  "md5": "5d301ec55c5ba4ea44d5492bf5053814",
  "version": "9.2.28"
 },
 {
  "android": "8.0",
  "codename": "capricorn",
  "device": "Mi 5s Global",
  "download": "http://bigota.d.miui.com/9.2.28/capricorn_global_images_9.2.28_20190228.0000.00_8.0_global_56c5a62253.tgz",
  "filename": "capricorn_global_images_9.2.28_20190228.0000.00_8.0_global_56c5a62253.tgz",
  "filesize": "1.7G",
  "md5": "56c5a622532541382ab0e271c9e6fe7a",
  "version": "9.2.28"
 },
 {
  "android": "8.1",
  "codename": "cereus",
  "device": "Redmi 6 China",
  "download": "http://bigota.d.miui.com/9.2.21/cereus_images_9.2.21_20190221.0000.00_8.1_cn_694c75c5d7.tgz",
  "filename": "cereus_images_9.2.21_20190221.0000.00_8.1_cn_694c75c5d7.tgz",
  "filesize": "1.9G",
  "md5": "694c75c5d70da95fb4e00db44b093d64",
  "version": "9.2.21"
 },
 {
  "android": "8.1",
  "codename": "cereus",
  "device": "Redmi 6 Global",
  "download": "http://bigota.d.miui.com/9.2.21/cereus_global_images_9.2.21_20190221.0000.00_8.1_global_963cadeea3.tgz",
  "filename": "cereus_global_images_9.2.21_20190221.0000.00_8.1_global_963cadeea3.tgz",
  "filesize": "1.8G",
  "md5": "963cadeea38fc16474b1996573463f81",
  "version": "9.2.21"
 },
 {
  "android": "8.0",
  "codename": "chiron",
  "device": "Mi MIX 2 China",
  "download": "http://bigota.d.miui.com/9.2.28/chiron_images_9.2.28_20190228.0000.00_8.0_cn_2bd711e875.tgz",
  "filename": "chiron_images_9.2.28_20190228.0000.00_8.0_cn_2bd711e875.tgz",
  "filesize": "2.3G",
  "md5": "2bd711e8758cc5cd5378e3ced1d56821",
  "version": "9.2.28"
 },
 {
  "android": "8.0",
  "codename": "chiron",
  "device": "Mi MIX 2 Global",
  "download": "http://bigota.d.miui.com/9.2.28/chiron_global_images_9.2.28_20190228.0000.00_8.0_global_89dd48df7c.tgz",
  "filename": "chiron_global_images_9.2.28_20190228.0000.00_8.0_global_89dd48df7c.tgz",
  "filesize": "2.0G",
  "md5": "89dd48df7ce62a4e96015806aeac670e",
  "version": "9.2.28"
 },
 {
  "android": "8.1",
  "codename": "clover",
  "device": "Mi Pad 4 (Plus) China",
  "download": "http://bigota.d.miui.com/9.2.28/clover_images_9.2.28_20190228.0000.00_8.1_cn_99bc91123c.tgz",
  "filename": "clover_images_9.2.28_20190228.0000.00_8.1_cn_99bc91123c.tgz",
  "filesize": "1.5G",
  "md5": "99bc91123c3b2f40e744106791d4c587",
  "version": "9.2.28"
 },
 {
  "android": "9.0",
  "codename": "dipper",
  "device": "Mi 8 China",
  "download": "http://bigota.d.miui.com/9.2.21/dipper_images_9.2.21_20190221.0000.00_9.0_cn_d503905ab9.tgz",
  "filename": "dipper_images_9.2.21_20190221.0000.00_9.0_cn_d503905ab9.tgz",
  "filesize": "2.7G",
  "md5": "d503905ab9cc0c4d1dc6e236d8719e61",
  "version": "9.2.21"
 },
 {
  "android": "9.0",
  "codename": "dipper",
  "device": "Mi 8 Global",
  "download": "http://bigota.d.miui.com/9.2.21/dipper_global_images_9.2.21_20190221.0000.00_9.0_global_4c00e625fa.tgz",
  "filename": "dipper_global_images_9.2.21_20190221.0000.00_9.0_global_4c00e625fa.tgz",
  "filesize": "2.5G",
  "md5": "4c00e625faeb76bbc37c9bfcbd39f29b",
  "version": "9.2.21"
 },
 {
  "android": "9.0",
  "codename": "equuleus",
  "device": "Mi 8 Pro China",
  "download": "http://bigota.d.miui.com/9.2.21/equuleus_images_9.2.21_20190221.0000.00_9.0_cn_98d947b04d.tgz",
  "filename": "equuleus_images_9.2.21_20190221.0000.00_9.0_cn_98d947b04d.tgz",
  "filesize": "2.7G",
  "md5": "98d947b04d0818de3b34769c5bc7e494",
  "version": "9.2.21"
 },
 {
  "android": "9.0",
  "codename": "equuleus",
  "device": "Mi 8 Pro Global",
  "download": "http://bigota.d.miui.com/9.2.21/equuleus_global_images_9.2.21_20190221.0000.00_9.0_global_8a083a8aef.tgz",
  "filename": "equuleus_global_images_9.2.21_20190221.0000.00_9.0_global_8a083a8aef.tgz",
  "filesize": "2.5G",
  "md5": "8a083a8aefa6b58a428fd22d50a0e77b",
  "version": "9.2.21"
 },
 {
  "android": "7.0",
  "codename": "helium",
  "device": "Mi Max Prime China",
  "download": "http://bigota.d.miui.com/9.2.28/helium_images_9.2.28_20190228.0000.00_7.0_cn_429066e956.tgz",
  "filename": "helium_images_9.2.28_20190228.0000.00_7.0_cn_429066e956.tgz",
  "filesize": "1.7G",
  "md5": "429066e956b1097643605a7f53b5ac12",
  "version": "9.2.28"
 },
 {
  "android": "7.0",
  "codename": "helium",
  "device": "Mi Max Prime Global",
  "download": "http://bigota.d.miui.com/9.2.28/helium_global_images_9.2.28_20190228.0000.00_7.0_global_746c582264.tgz",
  "filename": "helium_global_images_9.2.28_20190228.0000.00_7.0_global_746c582264.tgz",
  "filesize": "1.7G",
  "md5": "746c5822644eefd47135e718813c33ca",
  "version": "9.2.28"
 },
 {
  "android": "7.0",
  "codename": "hydrogen",
  "device": "Mi Max China",
  "download": "http://bigota.d.miui.com/9.2.28/hydrogen_images_9.2.28_20190228.0000.00_7.0_cn_b0425cbf68.tgz",
  "filename": "hydrogen_images_9.2.28_20190228.0000.00_7.0_cn_b0425cbf68.tgz",
  "filesize": "1.7G",
  "md5": "b0425cbf68d56757fd3bd9b3633a4f3a",
  "version": "9.2.28"
 },
 {
  "android": "7.0",
  "codename": "hydrogen",
  "device": "Mi Max Global",
  "download": "http://bigota.d.miui.com/9.2.28/hydrogen_global_images_9.2.28_20190228.0000.00_7.0_global_dc1f4a0adc.tgz",
  "filename": "hydrogen_global_images_9.2.28_20190228.0000.00_7.0_global_dc1f4a0adc.tgz",
  "filesize": "1.7G",
  "md5": "dc1f4a0adcc43d39258954eca109ce6a",
  "version": "9.2.28"
 },
 {
  "android": "8.1",
  "codename": "jason",
  "device": "Mi Note 3 China",
  "download": "http://bigota.d.miui.com/9.2.28/jason_images_9.2.28_20190228.0000.00_8.1_cn_09cbf1c0e4.tgz",
  "filename": "jason_images_9.2.28_20190228.0000.00_8.1_cn_09cbf1c0e4.tgz",
  "filesize": "2.4G",
  "md5": "09cbf1c0e45d28cead59155fac6699b8",
  "version": "9.2.28"
 },
 {
  "android": "8.1",
  "codename": "jason",
  "device": "Mi Note 3 Global",
  "download": "http://bigota.d.miui.com/9.2.28/jason_global_images_9.2.28_20190228.0000.00_8.1_global_bad35eac8f.tgz",
  "filename": "jason_global_images_9.2.28_20190228.0000.00_8.1_global_bad35eac8f.tgz",
  "filesize": "2.0G",
  "md5": "bad35eac8f2bb170d2c31bf5285a5d0b",
  "version": "9.2.28"
 },
 {
  "android": "6.0",
  "codename": "kate",
  "device": "Redmi Note 3 SE Global",
  "download": "http://bigota.d.miui.com/9.2.28/kate_global_images_9.2.28_20190228.0000.00_6.0_global_5f9701e275.tgz",
  "filename": "kate_global_images_9.2.28_20190228.0000.00_6.0_global_5f9701e275.tgz",
  "filesize": "1.4G",
  "md5": "5f9701e275f500dd11b465038593a51b",
  "version": "9.2.28"
 },
 {
  "android": "6.0",
  "codename": "land",
  "device": "Redmi 3S China",
  "download": "http://bigota.d.miui.com/9.2.28/land_images_9.2.28_20190228.0000.00_6.0_cn_5e4a6a9afa.tgz",
  "filename": "land_images_9.2.28_20190228.0000.00_6.0_cn_5e4a6a9afa.tgz",
  "filesize": "1.7G",
  "md5": "5e4a6a9afa4bef4931c537cdefb43895",
  "version": "9.2.28"
 },
 {
  "android": "6.0",
  "codename": "land",
  "device": "Redmi 3S Global",
  "download": "http://bigota.d.miui.com/9.2.28/land_global_images_9.2.28_20190228.0000.00_6.0_global_16e8610fe2.tgz",
  "filename": "land_global_images_9.2.28_20190228.0000.00_6.0_global_16e8610fe2.tgz",
  "filesize": "1.5G",
  "md5": "16e8610fe23f50602611d26a100a6f85",
  "version": "9.2.28"
 },
 {
  "android": "8.0",
  "codename": "lithium",
  "device": "Mi MIX China",
  "download": "http://bigota.d.miui.com/9.2.28/lithium_images_9.2.28_20190228.0000.00_8.0_cn_a632c95020.tgz",
  "filename": "lithium_images_9.2.28_20190228.0000.00_8.0_cn_a632c95020.tgz",
  "filesize": "1.8G",
  "md5": "a632c950205ce1f65160f96cb7d55969",
  "version": "9.2.28"
 },
 {
  "android": "8.0",
  "codename": "lithium",
  "device": "Mi MIX Global",
  "download": "http://bigota.d.miui.com/9.2.28/lithium_global_images_9.2.28_20190228.0000.00_8.0_global_0bc4ef9c16.tgz",
  "filename": "lithium_global_images_9.2.28_20190228.0000.00_8.0_global_0bc4ef9c16.tgz",
  "filesize": "1.7G",
  "md5": "0bc4ef9c16f74cfd8ba5f4b3e416f808",
  "version": "9.2.28"
 },
 {
  "android": "8.1",
  "codename": "lotus",
  "device": "Mi Play",
  "download": "http://bigota.d.miui.com/9.2.21/lotus_images_9.2.21_20190221.0000.00_8.1_cn_59aa2d9fd3.tgz",
  "filename": "lotus_images_9.2.21_20190221.0000.00_8.1_cn_59aa2d9fd3.tgz",
  "filesize": "2.3G",
  "md5": "59aa2d9fd3015912d9d0f0cbf39dc320",
  "version": "9.2.21"
 },
 {
  "android": "6.0",
  "codename": "markw",
  "device": "Redmi 4 Prime China",
  "download": "http://bigota.d.miui.com/9.2.28/markw_images_9.2.28_20190228.0000.00_6.0_cn_64311a479b.tgz",
  "filename": "markw_images_9.2.28_20190228.0000.00_6.0_cn_64311a479b.tgz",
  "filesize": "1.7G",
  "md5": "64311a479b9c5280edbde2b742ed1cd8",
  "version": "9.2.28"
 },
 {
  "android": "7.1",
  "codename": "meri",
  "device": "Mi 5C China",
  "download": "http://bigota.d.miui.com/9.2.28/meri_images_9.2.28_20190228.0000.00_7.1_cn_7429cb9130.tgz",
  "filename": "meri_images_9.2.28_20190228.0000.00_7.1_cn_7429cb9130.tgz",
  "filesize": "1.6G",
  "md5": "7429cb9130ea8d5bc842bcd846205007",
  "version": "9.2.28"
 },
 {
  "android": "7.0",
  "codename": "mido",
  "device": "Redmi Note 4 China",
  "download": "http://bigota.d.miui.com/9.2.28/mido_images_9.2.28_20190228.0000.00_7.0_cn_5b503a3b71.tgz",
  "filename": "mido_images_9.2.28_20190228.0000.00_7.0_cn_5b503a3b71.tgz",
  "filesize": "1.9G",
  "md5": "5b503a3b710613a2094009e480b9cfa8",
  "version": "9.2.28"
 },
 {
  "android": "7.0",
  "codename": "mido",
  "device": "Redmi Note 4 Global",
  "download": "http://bigota.d.miui.com/8.12.20/mido_global_images_8.12.20_20181220.0000.00_7.0_global_3947ba5143.tgz",
  "filename": "mido_global_images_8.12.20_20181220.0000.00_7.0_global_3947ba5143.tgz",
  "filesize": "1.8G",
  "md5": "3947ba5143005eb155341ee364c388e6",
  "version": "8.12.20"
 },
 {
  "android": "8.0",
  "codename": "natrium",
  "device": "Mi 5s Plus China",
  "download": "http://bigota.d.miui.com/9.2.28/natrium_images_9.2.28_20190228.0000.00_8.0_cn_10f55797cf.tgz",
  "filename": "natrium_images_9.2.28_20190228.0000.00_8.0_cn_10f55797cf.tgz",
  "filesize": "1.9G",
  "md5": "10f55797cf56aa29eb5423ca7abba78d",
  "version": "9.2.28"
 },
 {
  "android": "8.0",
  "codename": "natrium",
  "device": "Mi 5s Plus Global",
  "download": "http://bigota.d.miui.com/9.2.28/natrium_global_images_9.2.28_20190228.0000.00_8.0_global_e3fd849b5a.tgz",
  "filename": "natrium_global_images_9.2.28_20190228.0000.00_8.0_global_e3fd849b5a.tgz",
  "filesize": "1.8G",
  "md5": "e3fd849b5ae878d1596b6552ffb7a7b2",
  "version": "9.2.28"
 },
 {
  "android": "6.0",
  "codename": "nikel",
  "device": "Redmi Note 4 MTK China",
  "download": "http://bigota.d.miui.com/9.2.28/nikel_images_9.2.28_20190228.0000.00_6.0_cn_106d1fab68.tgz",
  "filename": "nikel_images_9.2.28_20190228.0000.00_6.0_cn_106d1fab68.tgz",
  "filesize": "1.7G",
  "md5": "106d1fab6820909f7c955def76f08dfa",
  "version": "9.2.28"
 },
 {
  "android": "6.0",
  "codename": "nikel",
  "device": "Redmi Note 4 MTK Global",
  "download": "http://bigota.d.miui.com/9.2.28/nikel_global_images_9.2.28_20190228.0000.00_6.0_global_4db6dbdfc3.tgz",
  "filename": "nikel_global_images_9.2.28_20190228.0000.00_6.0_global_4db6dbdfc3.tgz",
  "filesize": "1.6G",
  "md5": "4db6dbdfc3a5dfa5cda3ca43db6a304a",
  "version": "9.2.28"
 },
 {
  "android": "9.0",
  "codename": "nitrogen",
  "device": "Mi Max 3 China",
  "download": "http://bigota.d.miui.com/9.2.21/nitrogen_images_9.2.21_20190221.0000.00_9.0_cn_fb81189e6d.tgz",
  "filename": "nitrogen_images_9.2.21_20190221.0000.00_9.0_cn_fb81189e6d.tgz",
  "filesize": "2.6G",
  "md5": "fb81189e6d59021c71cdaa3930d483d4",
  "version": "9.2.21"
 },
 {
  "android": "9.0",
  "codename": "nitrogen",
  "device": "Mi Max 3 Global",
  "download": "http://bigota.d.miui.com/9.2.21/nitrogen_global_images_9.2.21_20190221.0000.00_9.0_global_1087feb8a2.tgz",
  "filename": "nitrogen_global_images_9.2.21_20190221.0000.00_9.0_global_1087feb8a2.tgz",
  "filesize": "2.5G",
  "md5": "1087feb8a2fee77b75af1b4e2d4df628",
  "version": "9.2.21"
 },
 {
  "android": "7.1",
  "codename": "oxygen",
  "device": "Mi Max 2 China",
  "download": "http://bigota.d.miui.com/9.2.28/oxygen_images_9.2.28_20190228.0000.00_7.1_cn_6c789450ac.tgz",
  "filename": "oxygen_images_9.2.28_20190228.0000.00_7.1_cn_6c789450ac.tgz",
  "filesize": "2.2G",
  "md5": "6c789450ac850b3b06ba327fbe20224f",
  "version": "9.2.28"
 },
 {
  "android": "7.1",
  "codename": "oxygen",
  "device": "Mi Max 2 Global",
  "download": "http://bigota.d.miui.com/9.2.28/oxygen_global_images_9.2.28_20190228.0000.00_7.1_global_62bc6a840e.tgz",
  "filename": "oxygen_global_images_9.2.28_20190228.0000.00_7.1_global_62bc6a840e.tgz",
  "filesize": "2.0G",
  "md5": "62bc6a840ebc4f9cd0d1cc91627ea45f",
  "version": "9.2.28"
 },
 {
  "android": "9.0",
  "codename": "perseus",
  "device": "Mi MIX 3 China",
  "download": "http://bigota.d.miui.com/9.2.21/perseus_images_9.2.21_20190221.0000.00_9.0_cn_b9d8fac89b.tgz",
  "filename": "perseus_images_9.2.21_20190221.0000.00_9.0_cn_b9d8fac89b.tgz",
  "filesize": "2.9G",
  "md5": "b9d8fac89be399950e580483b547843e",
  "version": "9.2.21"
 },
 {
  "android": "9.0",
  "codename": "platina",
  "device": "Mi 8 Lite China",
  "download": "http://bigota.d.miui.com/9.2.21/platina_images_9.2.21_20190221.0000.00_9.0_cn_fabd86ec09.tgz",
  "filename": "platina_images_9.2.21_20190221.0000.00_9.0_cn_fabd86ec09.tgz",
  "filesize": "2.7G",
  "md5": "fabd86ec095a886a8e90761a35b7566a",
  "version": "9.2.21"
 },
 {
  "android": "9.0",
  "codename": "platina",
  "device": "Mi 8 Lite Global",
  "download": "http://bigota.d.miui.com/9.2.21/platina_global_images_9.2.21_20190221.0000.00_9.0_global_889823fcef.tgz",
  "filename": "platina_global_images_9.2.21_20190221.0000.00_9.0_global_889823fcef.tgz",
  "filesize": "2.4G",
  "md5": "889823fcefc5f24212a5eacb64cc0a81",
  "version": "9.2.21"
 },
 {
  "android": "9.0",
  "codename": "polaris",
  "device": "Mi MIX 2S China",
  "download": "http://bigota.d.miui.com/9.2.28/polaris_images_9.2.28_20190228.0000.00_9.0_cn_5af006c71d.tgz",
  "filename": "polaris_images_9.2.28_20190228.0000.00_9.0_cn_5af006c71d.tgz",
  "filesize": "2.6G",
  "md5": "5af006c71d3eb049e98f164eec6d93cc",
  "version": "9.2.28"
 },
 {
  "android": "9.0",
  "codename": "polaris",
  "device": "Mi MIX 2S Global",
  "download": "http://bigota.d.miui.com/9.2.28/polaris_global_images_9.2.28_20190228.0000.00_9.0_global_3b5d593191.tgz",
  "filename": "polaris_global_images_9.2.28_20190228.0000.00_9.0_global_3b5d593191.tgz",
  "filesize": "2.5G",
  "md5": "3b5d5931918a73df8d2b5aad8bc1ae32",
  "version": "9.2.28"
 },
 {
  "android": "6.0",
  "codename": "prada",
  "device": "Redmi 4 China",
  "download": "http://bigota.d.miui.com/9.2.28/prada_images_9.2.28_20190228.0000.00_6.0_cn_ed061d3df3.tgz",
  "filename": "prada_images_9.2.28_20190228.0000.00_6.0_cn_ed061d3df3.tgz",
  "filesize": "1.7G",
  "md5": "ed061d3df3049b72269e0ae361abbf26",
  "version": "9.2.28"
 },
 {
  "android": "8.1",
  "codename": "riva",
  "device": "Redmi 5A China",
  "download": "http://bigota.d.miui.com/9.2.21/riva_images_9.2.21_20190221.0000.00_8.1_cn_ab6809f308.tgz",
  "filename": "riva_images_9.2.21_20190221.0000.00_8.1_cn_ab6809f308.tgz",
  "filesize": "1.9G",
  "md5": "ab6809f308335112d06be606771fdc36",
  "version": "9.2.21"
 },
 {
  "android": "8.1",
  "codename": "riva",
  "device": "Redmi 5A Global",
  "download": "http://bigota.d.miui.com/9.2.21/riva_global_images_9.2.21_20190221.0000.00_8.1_global_98891c5cc6.tgz",
  "filename": "riva_global_images_9.2.21_20190221.0000.00_8.1_global_98891c5cc6.tgz",
  "filesize": "1.9G",
  "md5": "98891c5cc601de7240ee7554cdd54a2a",
  "version": "9.2.21"
 },
 {
  "android": "6.0",
  "codename": "rolex",
  "device": "Redmi 4A China",
  "download": "http://bigota.d.miui.com/9.2.28/rolex_images_9.2.28_20190228.0000.00_6.0_cn_2f81126b58.tgz",
  "filename": "rolex_images_9.2.28_20190228.0000.00_6.0_cn_2f81126b58.tgz",
  "filesize": "1.7G",
  "md5": "2f81126b589288b535a895ff3770c9ba",
  "version": "9.2.28"
 },
 {
  "android": "7.1",
  "codename": "rolex",
  "device": "Redmi 4A Global",
  "download": "http://bigota.d.miui.com/9.2.28/rolex_global_images_9.2.28_20190228.0000.00_7.1_global_6c355316f3.tgz",
  "filename": "rolex_global_images_9.2.28_20190228.0000.00_7.1_global_6c355316f3.tgz",
  "filesize": "1.7G",
  "md5": "6c355316f3eeaddf5333776660b2d6b7",
  "version": "9.2.28"
 },
 {
  "android": "8.1",
  "codename": "rosy",
  "device": "Redmi 5 China",
  "download": "http://bigota.d.miui.com/9.2.21/rosy_images_9.2.21_20190221.0000.00_8.1_cn_2235d0ba42.tgz",
  "filename": "rosy_images_9.2.21_20190221.0000.00_8.1_cn_2235d0ba42.tgz",
  "filesize": "1.9G",
  "md5": "2235d0ba425e576ef05655e5cfe5a608",
  "version": "9.2.21"
 },
 {
  "android": "8.1",
  "codename": "rosy",
  "device": "Redmi 5 Global",
  "download": "http://bigota.d.miui.com/9.2.21/rosy_global_images_9.2.21_20190221.0000.00_8.1_global_d08bcb44df.tgz",
  "filename": "rosy_global_images_9.2.21_20190221.0000.00_8.1_global_d08bcb44df.tgz",
  "filesize": "1.9G",
  "md5": "d08bcb44df78a3b8b42786eb745e17cc",
  "version": "9.2.21"
 },
 {
  "android": "8.0",
  "codename": "sagit",
  "device": "Mi 6 China",
  "download": "http://bigota.d.miui.com/9.2.28/sagit_images_9.2.28_20190228.0000.00_8.0_cn_fae2a84cd4.tgz",
  "filename": "sagit_images_9.2.28_20190228.0000.00_8.0_cn_fae2a84cd4.tgz",
  "filesize": "2.2G",
  "md5": "fae2a84cd47cd9b4837141a1ea172ae7",
  "version": "9.2.28"
 },
 {
  "android": "8.0",
  "codename": "sagit",
  "device": "Mi 6 Global",
  "download": "http://bigota.d.miui.com/9.2.28/sagit_global_images_9.2.28_20190228.0000.00_8.0_global_80249a36e8.tgz",
  "filename": "sagit_global_images_9.2.28_20190228.0000.00_8.0_global_80249a36e8.tgz",
  "filesize": "1.9G",
  "md5": "80249a36e87bf0b186023aa8522c3eae",
  "version": "9.2.28"
 },
 {
  "android": "9.0",
  "codename": "sakura",
  "device": "Redmi 6 Pro China",
  "download": "http://bigota.d.miui.com/9.2.28/sakura_images_9.2.28_20190228.0000.00_9.0_cn_944b0a02c4.tgz",
  "filename": "sakura_images_9.2.28_20190228.0000.00_9.0_cn_944b0a02c4.tgz",
  "filesize": "2.3G",
  "md5": "944b0a02c4f2ee90a6aba2594952d8e1",
  "version": "9.2.28"
 },
 {
  "android": "8.1",
  "codename": "sakura",
  "device": "Redmi 6 Pro India",
  "download": "http://bigota.d.miui.com/9.2.21/sakura_india_global_images_9.2.21_20190221.0000.00_8.1_global_09161dcaf3.tgz",
  "filename": "sakura_india_global_images_9.2.21_20190221.0000.00_8.1_global_09161dcaf3.tgz",
  "filesize": "1.9G",
  "md5": "09161dcaf30e8bacbbff5a68e5cb7bd0",
  "version": "9.2.21"
 },
 {
  "android": "7.1",
  "codename": "santoni",
  "device": "Redmi 4X China",
  "download": "http://bigota.d.miui.com/9.2.28/santoni_images_9.2.28_20190228.0000.00_7.1_cn_9b4c2e3f4f.tgz",
  "filename": "santoni_images_9.2.28_20190228.0000.00_7.1_cn_9b4c2e3f4f.tgz",
  "filesize": "1.8G",
  "md5": "9b4c2e3f4fca57801dafcbcbb21be4ad",
  "version": "9.2.28"
 },
 {
  "android": "7.1",
  "codename": "santoni",
  "device": "Redmi 4X Global",
  "download": "http://bigota.d.miui.com/9.2.28/santoni_global_images_9.2.28_20190228.0000.00_7.1_global_c5270bcd58.tgz",
  "filename": "santoni_global_images_9.2.28_20190228.0000.00_7.1_global_c5270bcd58.tgz",
  "filesize": "1.7G",
  "md5": "c5270bcd58810bb87272bb5d13571803",
  "version": "9.2.28"
 },
 {
  "android": "8.0",
  "codename": "scorpio",
  "device": "Mi Note 2 China",
  "download": "http://bigota.d.miui.com/9.2.28/scorpio_images_9.2.28_20190228.0000.00_8.0_cn_c8cb171d12.tgz",
  "filename": "scorpio_images_9.2.28_20190228.0000.00_8.0_cn_c8cb171d12.tgz",
  "filesize": "1.9G",
  "md5": "c8cb171d1241d8f7840abe7ba515caf1",
  "version": "9.2.28"
 },
 {
  "android": "8.0",
  "codename": "scorpio",
  "device": "Mi Note 2 Global",
  "download": "http://bigota.d.miui.com/9.2.28/scorpio_global_images_9.2.28_20190228.0000.00_8.0_global_b626965e20.tgz",
  "filename": "scorpio_global_images_9.2.28_20190228.0000.00_8.0_global_b626965e20.tgz",
  "filesize": "1.7G",
  "md5": "b626965e201b69254a64f491ec068dab",
  "version": "9.2.28"
 },
 {
  "android": "9.0",
  "codename": "sirius",
  "device": "Mi 8 SE China",
  "download": "http://bigota.d.miui.com/9.2.15/sirius_images_9.2.15_20190215.0000.00_9.0_cn_17aade9cb9.tgz",
  "filename": "sirius_images_9.2.15_20190215.0000.00_9.0_cn_17aade9cb9.tgz",
  "filesize": "2.6G",
  "md5": "17aade9cb932625677030b5b37527696",
  "version": "9.2.15"
 },
 {
  "android": "8.1",
  "codename": "tiffany",
  "device": "Mi 5X China",
  "download": "http://bigota.d.miui.com/9.2.21/tiffany_images_9.2.21_20190221.0000.00_8.1_cn_3659e1e014.tgz",
  "filename": "tiffany_images_9.2.21_20190221.0000.00_8.1_cn_3659e1e014.tgz",
  "filesize": "2.2G",
  "md5": "3659e1e01484e3fa52f67009600730af",
  "version": "9.2.21"
 },
 {
  "android": "8.1",
  "codename": "tulip",
  "device": "Redmi Note 6 Pro Global",
  "download": "http://bigota.d.miui.com/9.2.21/tulip_global_images_9.2.21_20190221.0000.00_8.1_global_df8a2b000a.tgz",
  "filename": "tulip_global_images_9.2.21_20190221.0000.00_8.1_global_df8a2b000a.tgz",
  "filesize": "2.5G",
  "md5": "df8a2b000abf5d15bd4cb2a61269d637",
  "version": "9.2.21"
 },
 {
  "android": "7.1",
  "codename": "ugg",
  "device": "Redmi Note 5A Prime China",
  "download": "http://bigota.d.miui.com/9.2.28/ugg_images_9.2.28_20190228.0000.00_7.1_cn_d7552f9439.tgz",
  "filename": "ugg_images_9.2.28_20190228.0000.00_7.1_cn_d7552f9439.tgz",
  "filesize": "1.9G",
  "md5": "d7552f94397bf5ab8da952eb2e81c707",
  "version": "9.2.28"
 },
 {
  "android": "7.1",
  "codename": "ugg",
  "device": "Redmi Note 5A Prime Global",
  "download": "http://bigota.d.miui.com/9.2.28/ugg_global_images_9.2.28_20190228.0000.00_7.1_global_f019cf51d6.tgz",
  "filename": "ugg_global_images_9.2.28_20190228.0000.00_7.1_global_f019cf51d6.tgz",
  "filesize": "1.8G",
  "md5": "f019cf51d68821390cc81d5f4232acfa",
  "version": "9.2.28"
 },
 {
  "android": "7.1",
  "codename": "ugglite",
  "device": "Redmi Note 5A (2GB) China",
  "download": "http://bigota.d.miui.com/9.2.28/ugglite_images_9.2.28_20190228.0000.00_7.1_cn_f4cf4637e4.tgz",
  "filename": "ugglite_images_9.2.28_20190228.0000.00_7.1_cn_f4cf4637e4.tgz",
  "filesize": "1.9G",
  "md5": "f4cf4637e47d7dba784d5e533484f4fd",
  "version": "9.2.28"
 },
 {
  "android": "7.1",
  "codename": "ugglite",
  "device": "Redmi Note 5A (2GB) Global",
  "download": "http://bigota.d.miui.com/9.2.28/ugglite_global_images_9.2.28_20190228.0000.00_7.1_global_44719c2bb6.tgz",
  "filename": "ugglite_global_images_9.2.28_20190228.0000.00_7.1_global_44719c2bb6.tgz",
  "filesize": "1.8G",
  "md5": "44719c2bb699344f2662a93ef7941823",
  "version": "9.2.28"
 },
 {
  "android": "9.0",
  "codename": "ursa",
  "device": "Mi 8 Explorer China",
  "download": "http://bigota.d.miui.com/9.2.21/ursa_images_9.2.21_20190221.0000.00_9.0_cn_bb4c88c9e2.tgz",
  "filename": "ursa_images_9.2.21_20190221.0000.00_9.0_cn_bb4c88c9e2.tgz",
  "filesize": "2.8G",
  "md5": "bb4c88c9e2b7dc2e17b23ae158d994f1",
  "version": "9.2.21"
 },
 {
  "android": "8.1",
  "codename": "vince",
  "device": "Redmi 5 Plus China",
  "download": "http://bigota.d.miui.com/9.2.21/vince_images_9.2.21_20190221.0000.00_8.1_cn_0328976822.tgz",
  "filename": "vince_images_9.2.21_20190221.0000.00_8.1_cn_0328976822.tgz",
  "filesize": "2.0G",
  "md5": "03289768222ba8b9696290939e8b551f",
  "version": "9.2.21"
 },
 {
  "android": "8.1",
  "codename": "vince",
  "device": "Redmi 5 Plus Global - Redmi Note 5 India",
  "download": "http://bigota.d.miui.com/8.11.15/vince_global_images_8.11.15_20181115.0000.00_8.1_global_5d64473c16.tgz",
  "filename": "vince_global_images_8.11.15_20181115.0000.00_8.1_global_5d64473c16.tgz",
  "filesize": "2.0G",
  "md5": "5d64473c161d816888fee242976a10b5",
  "version": "8.11.15"
 },
 {
  "android": "8.1",
  "codename": "wayne",
  "device": "Mi 6X China",
  "download": "http://bigota.d.miui.com/9.2.15/wayne_images_9.2.15_20190215.0000.00_8.1_cn_70d4f9f24a.tgz",
  "filename": "wayne_images_9.2.15_20190215.0000.00_8.1_cn_70d4f9f24a.tgz",
  "filesize": "2.6G",
  "md5": "70d4f9f24a4aaa4389d96e3a1904fc04",
  "version": "9.2.15"
 },
 {
  "android": "8.1",
  "codename": "whyred",
  "device": "Redmi Note 5 China",
  "download": "http://bigota.d.miui.com/9.2.15/whyred_images_9.2.15_20190215.0000.00_8.1_cn_bba088a278.tgz",
  "filename": "whyred_images_9.2.15_20190215.0000.00_8.1_cn_bba088a278.tgz",
  "filesize": "2.4G",
  "md5": "bba088a278b89b8fabe6535a534a8b76",
  "version": "9.2.15"
 },
 {
  "android": "8.1",
  "codename": "whyred",
  "device": "Redmi Note 5 Global - Redmi Note 5 Pro India",
  "download": "http://bigota.d.miui.com/9.2.21/whyred_global_images_9.2.21_20190221.0000.00_8.1_global_98dce58f16.tgz",
  "filename": "whyred_global_images_9.2.21_20190221.0000.00_8.1_global_98dce58f16.tgz",
  "filesize": "2.3G",
  "md5": "98dce58f16a7b3e4c2a97d31f78c6f32",
  "version": "9.2.21"
 },
 {
  "android": "8.1",
  "codename": "ysl",
  "device": "Redmi S2 China",
  "download": "http://bigota.d.miui.com/9.2.28/ysl_images_9.2.28_20190228.0000.00_8.1_cn_095ac64bf2.tgz",
  "filename": "ysl_images_9.2.28_20190228.0000.00_8.1_cn_095ac64bf2.tgz",
  "filesize": "1.9G",
  "md5": "095ac64bf2191739aa720d4f46d87a08",
  "version": "9.2.28"
 },
 {
  "android": "8.1",
  "codename": "ysl",
  "device": "Redmi S2 Global - Redmi Y2",
  "download": "http://bigota.d.miui.com/9.2.21/ysl_global_images_9.2.21_20190221.0000.00_8.1_global_d5efbc212d.tgz",
  "filename": "ysl_global_images_9.2.21_20190221.0000.00_8.1_global_d5efbc212d.tgz",
  "filesize": "1.8G",
  "md5": "d5efbc212da48be4ce2b442ed692a661",
  "version": "9.2.21"
 }
]