[
 {
  "android": "9.0",
  "codename": "beryllium",
  "device": "POCOF1Global",
  "download": "http://bigota.d.miui.com/8.12.27/miui_POCOF1Global_8.12.27_fe9f53ea84_9.0.zip",
  "filename": "miui_POCOF1Global_8.12.27_fe9f53ea84_9.0.zip",
  "version": "8.12.27"
 },
 {
  "android": "8.1",
  "codename": "cactus",
  "device": "HM6A",
  "download": "http://bigota.d.miui.com/8.12.20/miui_HM6A_8.12.20_65a647b79d_8.1.zip",
  "filename": "miui_HM6A_8.12.20_65a647b79d_8.1.zip",
  "version": "8.12.20"
 },
 {
  "android": "8.1",
  "codename": "cactus",
  "device": "HM6AGlobal",
  "download": "http://bigota.d.miui.com/8.12.27/miui_HM6AGlobal_8.12.27_60fb7db1ef_8.1.zip",
  "filename": "miui_HM6AGlobal_8.12.27_60fb7db1ef_8.1.zip",
  "version": "8.12.27"
 },
 {
  "android": "7.0",
  "codename": "cappu",
  "device": "MIPAD3",
  "download": "http://bigota.d.miui.com/8.12.27/miui_MIPAD3_8.12.27_88695a3c70_7.0.zip",
  "filename": "miui_MIPAD3_8.12.27_88695a3c70_7.0.zip",
  "version": "8.12.27"
 },
 {
  "android": "8.0",
  "codename": "capricorn",
  "device": "MI5S",
  "download": "http://bigota.d.miui.com/8.12.20/miui_MI5S_8.12.20_b5dd9e3a3a_8.0.zip",
  "filename": "miui_MI5S_8.12.20_b5dd9e3a3a_8.0.zip",
  "version": "8.12.20"
 },
 {
  "android": "8.0",
  "codename": "capricorn",
  "device": "MI5SGlobal",
  "download": "http://bigota.d.miui.com/8.12.27/miui_MI5SGlobal_8.12.27_dd1b17891d_8.0.zip",
  "filename": "miui_MI5SGlobal_8.12.27_dd1b17891d_8.0.zip",
  "version": "8.12.27"
 },
 {
  "android": "8.1",
  "codename": "cereus",
  "device": "HM6",
  "download": "http://bigota.d.miui.com/8.12.20/miui_HM6_8.12.20_3c5e43da9b_8.1.zip",
  "filename": "miui_HM6_8.12.20_3c5e43da9b_8.1.zip",
  "version": "8.12.20"
 },
 {
  "android": "8.1",
  "codename": "cereus",
  "device": "HM6Global",
  "download": "http://bigota.d.miui.com/8.12.27/miui_HM6Global_8.12.27_5dc13d12db_8.1.zip",
  "filename": "miui_HM6Global_8.12.27_5dc13d12db_8.1.zip",
  "version": "8.12.27"
 },
 {
  "android": "8.0",
  "codename": "chiron",
  "device": "MIMIX2",
  "download": "http://bigota.d.miui.com/8.12.27/miui_MIMIX2_8.12.27_2b2f0fc584_8.0.zip",
  "filename": "miui_MIMIX2_8.12.27_2b2f0fc584_8.0.zip",
  "version": "8.12.27"
 },
 {
  "android": "8.0",
  "codename": "chiron",
  "device": "MIMIX2Global",
  "download": "http://bigota.d.miui.com/8.12.27/miui_MIMIX2Global_8.12.27_9e97799831_8.0.zip",
  "filename": "miui_MIMIX2Global_8.12.27_9e97799831_8.0.zip",
  "version": "8.12.27"
 },
 {
  "android": "8.1",
  "codename": "clover",
  "device": "MIPAD4",
  "download": "http://bigota.d.miui.com/8.12.20/miui_MIPAD4_8.12.20_37caedaed0_8.1.zip",
  "filename": "miui_MIPAD4_8.12.20_37caedaed0_8.1.zip",
  "version": "8.12.20"
 },
 {
  "android": "9.0",
  "codename": "dipper",
  "device": "MI8",
  "download": "http://bigota.d.miui.com/8.12.20/miui_MI8_8.12.20_07a903425c_9.0.zip",
  "filename": "miui_MI8_8.12.20_07a903425c_9.0.zip",
  "version": "8.12.20"
 },
 {
  "android": "9.0",
  "codename": "dipper",
  "device": "MI8Global",
  "download": "http://bigota.d.miui.com/8.12.20/miui_MI8Global_8.12.20_c7a9af8587_9.0.zip",
  "filename": "miui_MI8Global_8.12.20_c7a9af8587_9.0.zip",
  "version": "8.12.20"
 },
 {
  "android": "9.0",
  "codename": "equuleus",
  "device": "MI8UD",
  "download": "http://bigota.d.miui.com/8.12.20/miui_MI8UD_8.12.20_7f9ae47f39_9.0.zip",
  "filename": "miui_MI8UD_8.12.20_7f9ae47f39_9.0.zip",
  "version": "8.12.20"
 },
 {
  "android": "8.1",
  "codename": "equuleus",
  "device": "MI8UDGlobal",
  "download": "http://bigota.d.miui.com/8.12.6/miui_MI8UDGlobal_8.12.6_279335a737_8.1.zip",
  "filename": "miui_MI8UDGlobal_8.12.6_279335a737_8.1.zip",
  "version": "8.12.6"
 },
 {
  "android": "8.0",
  "codename": "gemini",
  "device": "MI5",
  "download": "http://bigota.d.miui.com/8.11.22/miui_MI5_8.11.22_f9ead04910_8.0.zip",
  "filename": "miui_MI5_8.11.22_f9ead04910_8.0.zip",
  "version": "8.11.22"
 },
 {
  "android": "8.0",
  "codename": "gemini",
  "device": "MI5Global",
  "download": "http://bigota.d.miui.com/8.11.22/miui_MI5Global_8.11.22_c5d7ee6745_8.0.zip",
  "filename": "miui_MI5Global_8.11.22_c5d7ee6745_8.0.zip",
  "version": "8.11.22"
 },
 {
  "android": "7.0",
  "codename": "helium",
  "device": "MIMAX652",
  "download": "http://bigota.d.miui.com/8.12.27/miui_MIMAX652_8.12.27_7fe43fe25a_7.0.zip",
  "filename": "miui_MIMAX652_8.12.27_7fe43fe25a_7.0.zip",
  "version": "8.12.27"
 },
 {
  "android": "7.0",
  "codename": "helium",
  "device": "MIMAX652Global",
  "download": "http://bigota.d.miui.com/8.12.27/miui_MIMAX652Global_8.12.27_2db90016a5_7.0.zip",
  "filename": "miui_MIMAX652Global_8.12.27_2db90016a5_7.0.zip",
  "version": "8.12.27"
 },
 {
  "android": "7.0",
  "codename": "hydrogen",
  "device": "MIMAX",
  "download": "http://bigota.d.miui.com/8.12.27/miui_MIMAX_8.12.27_bec4d719ca_7.0.zip",
  "filename": "miui_MIMAX_8.12.27_bec4d719ca_7.0.zip",
  "version": "8.12.27"
 },
 {
  "android": "7.0",
  "codename": "hydrogen",
  "device": "MIMAXGlobal",
  "download": "http://bigota.d.miui.com/8.12.27/miui_MIMAXGlobal_8.12.27_c28ff95b04_7.0.zip",
  "filename": "miui_MIMAXGlobal_8.12.27_c28ff95b04_7.0.zip",
  "version": "8.12.27"
 },
 {
  "android": "8.1",
  "codename": "jason",
  "device": "MINote3",
  "download": "http://bigota.d.miui.com/8.12.27/miui_MINote3_8.12.27_ba75754372_8.1.zip",
  "filename": "miui_MINote3_8.12.27_ba75754372_8.1.zip",
  "version": "8.12.27"
 },
 {
  "android": "8.1",
  "codename": "jason",
  "device": "MINote3Global",
  "download": "http://bigota.d.miui.com/8.12.27/miui_MINote3Global_8.12.27_c0342343e8_8.1.zip",
  "filename": "miui_MINote3Global_8.12.27_c0342343e8_8.1.zip",
  "version": "8.12.27"
 },
 {
  "android": "6.0",
  "codename": "kate",
  "device": "HMNote3ProtwGlobal",
  "download": "http://bigota.d.miui.com/8.12.27/miui_HMNote3ProtwGlobal_8.12.27_7ca5f371d0_6.0.zip",
  "filename": "miui_HMNote3ProtwGlobal_8.12.27_7ca5f371d0_6.0.zip",
  "version": "8.12.27"
 },
 {
  "android": "6.0",
  "codename": "kenzo",
  "device": "HMNote3Pro",
  "download": "http://bigota.d.miui.com/8.11.22/miui_HMNote3Pro_8.11.22_38aac9b24f_6.0.zip",
  "filename": "miui_HMNote3Pro_8.11.22_38aac9b24f_6.0.zip",
  "version": "8.11.22"
 },
 {
  "android": "6.0",
  "codename": "kenzo",
  "device": "HMNote3ProGlobal",
  "download": "http://bigota.d.miui.com/8.11.22/miui_HMNote3ProGlobal_8.11.22_ec10ddebd0_6.0.zip",
  "filename": "miui_HMNote3ProGlobal_8.11.22_ec10ddebd0_6.0.zip",
  "version": "8.11.22"
 },
 {
  "android": "6.0",
  "codename": "land",
  "device": "HM3S",
  "download": "http://bigota.d.miui.com/8.12.27/miui_HM3S_8.12.27_be52059f84_6.0.zip",
  "filename": "miui_HM3S_8.12.27_be52059f84_6.0.zip",
  "version": "8.12.27"
 },
 {
  "android": "6.0",
  "codename": "land",
  "device": "HM3SGlobal",
  "download": "http://bigota.d.miui.com/8.12.27/miui_HM3SGlobal_8.12.27_cf8294f03e_6.0.zip",
  "filename": "miui_HM3SGlobal_8.12.27_cf8294f03e_6.0.zip",
  "version": "8.12.27"
 },
 {
  "android": "8.0",
  "codename": "lithium",
  "device": "MIMIX",
  "download": "http://bigota.d.miui.com/8.12.27/miui_MIMIX_8.12.27_a0690eb7c3_8.0.zip",
  "filename": "miui_MIMIX_8.12.27_a0690eb7c3_8.0.zip",
  "version": "8.12.27"
 },
 {
  "android": "8.0",
  "codename": "lithium",
  "device": "MIMIXGlobal",
  "download": "http://bigota.d.miui.com/8.12.27/miui_MIMIXGlobal_8.12.27_882ddcbce4_8.0.zip",
  "filename": "miui_MIMIXGlobal_8.12.27_882ddcbce4_8.0.zip",
  "version": "8.12.27"
 },
 {
  "android": "6.0",
  "codename": "markw",
  "device": "HM4Pro",
  "download": "http://bigota.d.miui.com/8.12.27/miui_HM4Pro_8.12.27_2ae6e36d78_6.0.zip",
  "filename": "miui_HM4Pro_8.12.27_2ae6e36d78_6.0.zip",
  "version": "8.12.27"
 },
 {
  "android": "7.1",
  "codename": "meri",
  "device": "MI5C",
  "download": "http://bigota.d.miui.com/8.12.27/miui_MI5C_8.12.27_a0af38df56_7.1.zip",
  "filename": "miui_MI5C_8.12.27_a0af38df56_7.1.zip",
  "version": "8.12.27"
 },
 {
  "android": "7.0",
  "codename": "mido",
  "device": "HMNote4X",
  "download": "http://bigota.d.miui.com/8.12.27/miui_HMNote4X_8.12.27_c75eb3160f_7.0.zip",
  "filename": "miui_HMNote4X_8.12.27_c75eb3160f_7.0.zip",
  "version": "8.12.27"
 },
 {
  "android": "7.0",
  "codename": "mido",
  "device": "HMNote4XGlobal",
  "download": "http://bigota.d.miui.com/8.12.20/miui_HMNote4XGlobal_8.12.20_43a9a2079c_7.0.zip",
  "filename": "miui_HMNote4XGlobal_8.12.20_43a9a2079c_7.0.zip",
  "version": "8.12.20"
 },
 {
  "android": "8.0",
  "codename": "natrium",
  "device": "MI5SPlus",
  "download": "http://bigota.d.miui.com/8.12.20/miui_MI5SPlus_8.12.20_ef1dda590f_8.0.zip",
  "filename": "miui_MI5SPlus_8.12.20_ef1dda590f_8.0.zip",
  "version": "8.12.20"
 },
 {
  "android": "8.0",
  "codename": "natrium",
  "device": "MI5SPlusGlobal",
  "download": "http://bigota.d.miui.com/8.12.27/miui_MI5SPlusGlobal_8.12.27_f8e5f33e05_8.0.zip",
  "filename": "miui_MI5SPlusGlobal_8.12.27_f8e5f33e05_8.0.zip",
  "version": "8.12.27"
 },
 {
  "android": "6.0",
  "codename": "nikel",
  "device": "HMNote4",
  "download": "http://bigota.d.miui.com/8.12.27/miui_HMNote4_8.12.27_17795b01d6_6.0.zip",
  "filename": "miui_HMNote4_8.12.27_17795b01d6_6.0.zip",
  "version": "8.12.27"
 },
 {
  "android": "6.0",
  "codename": "nikel",
  "device": "HMNote4Global",
  "download": "http://bigota.d.miui.com/8.12.27/miui_HMNote4Global_8.12.27_b4fe2ed7a7_6.0.zip",
  "filename": "miui_HMNote4Global_8.12.27_b4fe2ed7a7_6.0.zip",
  "version": "8.12.27"
 },
 {
  "android": "9.0",
  "codename": "nitrogen",
  "device": "MIMAX3",
  "download": "http://bigota.d.miui.com/8.12.20/miui_MIMAX3_8.12.20_8f1887c220_9.0.zip",
  "filename": "miui_MIMAX3_8.12.20_8f1887c220_9.0.zip",
  "version": "8.12.20"
 },
 {
  "android": "8.1",
  "codename": "nitrogen",
  "device": "MIMAX3Global",
  "download": "http://bigota.d.miui.com/8.12.13/miui_MIMAX3Global_8.12.13_ec4e24afd9_8.1.zip",
  "filename": "miui_MIMAX3Global_8.12.13_ec4e24afd9_8.1.zip",
  "version": "8.12.13"
 },
 {
  "android": "6.0",
  "codename": "omega",
  "device": "HMPro",
  "download": "http://bigota.d.miui.com/8.12.27/miui_HMPro_8.12.27_96e4aa3dcb_6.0.zip",
  "filename": "miui_HMPro_8.12.27_96e4aa3dcb_6.0.zip",
  "version": "8.12.27"
 },
 {
  "android": "7.1",
  "codename": "oxygen",
  "device": "MIMAX2",
  "download": "http://bigota.d.miui.com/8.12.27/miui_MIMAX2_8.12.27_67c2d0774a_7.1.zip",
  "filename": "miui_MIMAX2_8.12.27_67c2d0774a_7.1.zip",
  "version": "8.12.27"
 },
 {
  "android": "7.1",
  "codename": "oxygen",
  "device": "MIMAX2Global",
  "download": "http://bigota.d.miui.com/8.12.27/miui_MIMAX2Global_8.12.27_60b3ef7f89_7.1.zip",
  "filename": "miui_MIMAX2Global_8.12.27_60b3ef7f89_7.1.zip",
  "version": "8.12.27"
 },
 {
  "android": "9.0",
  "codename": "perseus",
  "device": "MIMIX3",
  "download": "http://bigota.d.miui.com/8.12.20/miui_MIMIX3_8.12.20_f160ca90f6_9.0.zip",
  "filename": "miui_MIMIX3_8.12.20_f160ca90f6_9.0.zip",
  "version": "8.12.20"
 },
 {
  "android": "8.1",
  "codename": "platina",
  "device": "MI8Lite",
  "download": "http://bigota.d.miui.com/8.12.6/miui_MI8Lite_8.12.6_e345f76a33_8.1.zip",
  "filename": "miui_MI8Lite_8.12.6_e345f76a33_8.1.zip",
  "version": "8.12.6"
 },
 {
  "android": "8.1",
  "codename": "platina",
  "device": "MI8LiteGlobal",
  "download": "http://bigota.d.miui.com/8.12.27/miui_MI8LiteGlobal_8.12.27_f6045e3f61_8.1.zip",
  "filename": "miui_MI8LiteGlobal_8.12.27_f6045e3f61_8.1.zip",
  "version": "8.12.27"
 },
 {
  "android": "9.0",
  "codename": "polaris",
  "device": "MIMIX2S",
  "download": "http://bigota.d.miui.com/8.12.20/miui_MIMIX2S_8.12.20_fb5b1b05ab_9.0.zip",
  "filename": "miui_MIMIX2S_8.12.20_fb5b1b05ab_9.0.zip",
  "version": "8.12.20"
 },
 {
  "android": "9.0",
  "codename": "polaris",
  "device": "MIMIX2SGlobal",
  "download": "http://bigota.d.miui.com/8.12.27/miui_MIMIX2SGlobal_8.12.27_bbb5b3d06b_9.0.zip",
  "filename": "miui_MIMIX2SGlobal_8.12.27_bbb5b3d06b_9.0.zip",
  "version": "8.12.27"
 },
 {
  "android": "6.0",
  "codename": "prada",
  "device": "HM4",
  "download": "http://bigota.d.miui.com/8.12.27/miui_HM4_8.12.27_31960847c3_6.0.zip",
  "filename": "miui_HM4_8.12.27_31960847c3_6.0.zip",
  "version": "8.12.27"
 },
 {
  "android": "8.1",
  "codename": "riva",
  "device": "HM5A",
  "download": "http://bigota.d.miui.com/8.12.20/miui_HM5A_8.12.20_3f7fbfaaad_8.1.zip",
  "filename": "miui_HM5A_8.12.20_3f7fbfaaad_8.1.zip",
  "version": "8.12.20"
 },
 {
  "android": "8.1",
  "codename": "riva",
  "device": "HM5AGlobal",
  "download": "http://bigota.d.miui.com/8.12.27/miui_HM5AGlobal_8.12.27_88ba5f2cdf_8.1.zip",
  "filename": "miui_HM5AGlobal_8.12.27_88ba5f2cdf_8.1.zip",
  "version": "8.12.27"
 },
 {
  "android": "6.0",
  "codename": "rolex",
  "device": "HM4A",
  "download": "http://bigota.d.miui.com/8.12.27/miui_HM4A_8.12.27_acea341487_6.0.zip",
  "filename": "miui_HM4A_8.12.27_acea341487_6.0.zip",
  "version": "8.12.27"
 },
 {
  "android": "7.1",
  "codename": "rolex",
  "device": "HM4AGlobal",
  "download": "http://bigota.d.miui.com/8.12.27/miui_HM4AGlobal_8.12.27_a750eb3948_7.1.zip",
  "filename": "miui_HM4AGlobal_8.12.27_a750eb3948_7.1.zip",
  "version": "8.12.27"
 },
 {
  "android": "8.1",
  "codename": "rosy",
  "device": "HM5",
  "download": "http://bigota.d.miui.com/8.12.20/miui_HM5_8.12.20_2f05dabcde_8.1.zip",
  "filename": "miui_HM5_8.12.20_2f05dabcde_8.1.zip",
  "version": "8.12.20"
 },
 {
  "android": "8.1",
  "codename": "rosy",
  "device": "HM5Global",
  "download": "http://bigota.d.miui.com/8.12.27/miui_HM5Global_8.12.27_80b9432df0_8.1.zip",
  "filename": "miui_HM5Global_8.12.27_80b9432df0_8.1.zip",
  "version": "8.12.27"
 },
 {
  "android": "8.0",
  "codename": "sagit",
  "device": "MI6",
  "download": "http://bigota.d.miui.com/8.12.27/miui_MI6_8.12.27_5700fa5bd1_8.0.zip",
  "filename": "miui_MI6_8.12.27_5700fa5bd1_8.0.zip",
  "version": "8.12.27"
 },
 {
  "android": "8.0",
  "codename": "sagit",
  "device": "MI6Global",
  "download": "http://bigota.d.miui.com/8.12.27/miui_MI6Global_8.12.27_926d6ac9bb_8.0.zip",
  "filename": "miui_MI6Global_8.12.27_926d6ac9bb_8.0.zip",
  "version": "8.12.27"
 },
 {
  "android": "8.1",
  "codename": "sakura",
  "device": "HM6Pro",
  "download": "http://bigota.d.miui.com/8.12.20/miui_HM6Pro_8.12.20_4ad1662679_8.1.zip",
  "filename": "miui_HM6Pro_8.12.20_4ad1662679_8.1.zip",
  "version": "8.12.20"
 },
 {
  "android": "8.1",
  "codename": "sakura",
  "device": "HM6ProINGlobal",
  "download": "http://bigota.d.miui.com/8.12.27/miui_HM6ProINGlobal_8.12.27_e7f4251b5e_8.1.zip",
  "filename": "miui_HM6ProINGlobal_8.12.27_e7f4251b5e_8.1.zip",
  "version": "8.12.27"
 },
 {
  "android": "7.1",
  "codename": "santoni",
  "device": "HM4X",
  "download": "http://bigota.d.miui.com/8.12.27/miui_HM4X_8.12.27_2812555340_7.1.zip",
  "filename": "miui_HM4X_8.12.27_2812555340_7.1.zip",
  "version": "8.12.27"
 },
 {
  "android": "7.1",
  "codename": "santoni",
  "device": "HM4XGlobal",
  "download": "http://bigota.d.miui.com/8.12.27/miui_HM4XGlobal_8.12.27_91c8917e11_7.1.zip",
  "filename": "miui_HM4XGlobal_8.12.27_91c8917e11_7.1.zip",
  "version": "8.12.27"
 },
 {
  "android": "8.0",
  "codename": "scorpio",
  "device": "MINote2",
  "download": "http://bigota.d.miui.com/8.12.27/miui_MINote2_8.12.27_5f4bea83a9_8.0.zip",
  "filename": "miui_MINote2_8.12.27_5f4bea83a9_8.0.zip",
  "version": "8.12.27"
 },
 {
  "android": "8.0",
  "codename": "scorpio",
  "device": "MINote2Global",
  "download": "http://bigota.d.miui.com/8.12.27/miui_MINote2Global_8.12.27_55b8229959_8.0.zip",
  "filename": "miui_MINote2Global_8.12.27_55b8229959_8.0.zip",
  "version": "8.12.27"
 },
 {
  "android": "9.0",
  "codename": "sirius",
  "device": "MI8SE",
  "download": "http://bigota.d.miui.com/8.12.20/miui_MI8SE_8.12.20_b85fd149da_9.0.zip",
  "filename": "miui_MI8SE_8.12.20_b85fd149da_9.0.zip",
  "version": "8.12.20"
 },
 {
  "android": "8.1",
  "codename": "tiffany",
  "device": "MI5X",
  "download": "http://bigota.d.miui.com/8.12.20/miui_MI5X_8.12.20_97621b623c_8.1.zip",
  "filename": "miui_MI5X_8.12.20_97621b623c_8.1.zip",
  "version": "8.12.20"
 },
 {
  "android": "8.1",
  "codename": "tulip",
  "device": "HMNote6ProGlobal",
  "download": "http://bigota.d.miui.com/8.12.27/miui_HMNote6ProGlobal_8.12.27_67503705c6_8.1.zip",
  "filename": "miui_HMNote6ProGlobal_8.12.27_67503705c6_8.1.zip",
  "version": "8.12.27"
 },
 {
  "android": "7.1",
  "codename": "ugg",
  "device": "HMNote5A",
  "download": "http://bigota.d.miui.com/8.12.27/miui_HMNote5A_8.12.27_42acd89116_7.1.zip",
  "filename": "miui_HMNote5A_8.12.27_42acd89116_7.1.zip",
  "version": "8.12.27"
 },
 {
  "android": "7.1",
  "codename": "ugg",
  "device": "HMNote5AGlobal",
  "download": "http://bigota.d.miui.com/8.12.27/miui_HMNote5AGlobal_8.12.27_c7b69d1d75_7.1.zip",
  "filename": "miui_HMNote5AGlobal_8.12.27_c7b69d1d75_7.1.zip",
  "version": "8.12.27"
 },
 {
  "android": "7.1",
  "codename": "ugglite",
  "device": "HMNote5ALITE",
  "download": "http://bigota.d.miui.com/8.12.27/miui_HMNote5ALITE_8.12.27_a017a109fa_7.1.zip",
  "filename": "miui_HMNote5ALITE_8.12.27_a017a109fa_7.1.zip",
  "version": "8.12.27"
 },
 {
  "android": "7.1",
  "codename": "ugglite",
  "device": "HMNote5ALITEGlobal",
  "download": "http://bigota.d.miui.com/8.12.27/miui_HMNote5ALITEGlobal_8.12.27_4e3545d241_7.1.zip",
  "filename": "miui_HMNote5ALITEGlobal_8.12.27_4e3545d241_7.1.zip",
  "version": "8.12.27"
 },
 {
  "android": "9.0",
  "codename": "ursa",
  "device": "MI8Explorer",
  "download": "http://bigota.d.miui.com/8.12.20/miui_MI8Explorer_8.12.20_7795e7c872_9.0.zip",
  "filename": "miui_MI8Explorer_8.12.20_7795e7c872_9.0.zip",
  "version": "8.12.20"
 },
 {
  "android": "8.1",
  "codename": "vince",
  "device": "HM5Plus",
  "download": "http://bigota.d.miui.com/8.12.20/miui_HM5Plus_8.12.20_2f42719a27_8.1.zip",
  "filename": "miui_HM5Plus_8.12.20_2f42719a27_8.1.zip",
  "version": "8.12.20"
 },
 {
  "android": "8.1",
  "codename": "vince",
  "device": "HM5PlusGlobal",
  "download": "http://bigota.d.miui.com/8.11.15/miui_HM5PlusGlobal_8.11.15_dd40bfa136_8.1.zip",
  "filename": "miui_HM5PlusGlobal_8.11.15_dd40bfa136_8.1.zip",
  "version": "8.11.15"
 },
 {
  "android": "8.1",
  "codename": "wayne",
  "device": "MI6X",
  "download": "http://bigota.d.miui.com/8.12.20/miui_MI6X_8.12.20_2e0cc55431_8.1.zip",
  "filename": "miui_MI6X_8.12.20_2e0cc55431_8.1.zip",
  "version": "8.12.20"
 },
 {
  "android": "8.1",
  "codename": "whyred",
  "device": "HMNote5",
  "download": "http://bigota.d.miui.com/8.12.20/miui_HMNote5_8.12.20_aa5610312c_8.1.zip",
  "filename": "miui_HMNote5_8.12.20_aa5610312c_8.1.zip",
  "version": "8.12.20"
 },
 {
  "android": "8.1",
  "codename": "whyred",
  "device": "HMNote5HMNote5ProGlobal",
  "download": "http://bigota.d.miui.com/8.12.27/miui_HMNote5HMNote5ProGlobal_8.12.27_9d014dfd64_8.1.zip",
  "filename": "miui_HMNote5HMNote5ProGlobal_8.12.27_9d014dfd64_8.1.zip",
  "version": "8.12.27"
 },
 {
  "android": "8.1",
  "codename": "ysl",
  "device": "HMS2",
  "download": "http://bigota.d.miui.com/8.12.27/miui_HMS2_8.12.27_a0402ee08a_8.1.zip",
  "filename": "miui_HMS2_8.12.27_a0402ee08a_8.1.zip",
  "version": "8.12.27"
 },
 {
  "android": "8.1",
  "codename": "ysl",
  "device": "HMS2Global",
  "download": "http://bigota.d.miui.com/8.12.27/miui_HMS2Global_8.12.27_5cf5047d1f_8.1.zip",
  "filename": "miui_HMS2Global_8.12.27_5cf5047d1f_8.1.zip",
  "version": "8.12.27"
 }
]