{
 "sakura": {
  "9.8.9": "http://bigota.d.miui.com/9.8.9/miui_HM6Pro_9.8.9_a9e6debf25_9.0.zip",
  "9.8.22": "http://bigota.d.miui.com/9.8.22/miui_HM6Pro_9.8.22_1482d09240_9.0.zip",
  "9.8.15": "http://bigota.d.miui.com/9.8.15/miui_HM6Pro_9.8.15_0c9d29ed13_9.0.zip",
  "9.8.1": "http://bigota.d.miui.com/9.8.1/miui_HM6Pro_9.8.1_ddd35d9680_9.0.zip",
  "9.7.4": "http://bigota.d.miui.com/9.7.4/miui_HM6Pro_9.7.4_4691ef1c41_9.0.zip",
  "9.7.25": "http://bigota.d.miui.com/9.7.25/miui_HM6Pro_9.7.25_d065ccc0b9_9.0.zip",
  "9.7.18": "http://bigota.d.miui.com/9.7.18/miui_HM6Pro_9.7.18_8066701709_9.0.zip",
  "9.7.11": "http://bigota.d.miui.com/9.7.11/miui_HM6Pro_9.7.11_da88131d75_9.0.zip",
  "9.6.27": "http://bigota.d.miui.com/9.6.27/miui_HM6Pro_9.6.27_789c2ec9bd_9.0.zip",
  "9.6.20": "http://bigota.d.miui.com/9.6.20/miui_HM6Pro_9.6.20_573638cc2f_9.0.zip",
  "9.6.13": "http://bigota.d.miui.com/9.6.13/miui_HM6Pro_9.6.13_38161a1527_9.0.zip",
  "9.5.9": "http://bigota.d.miui.com/9.5.9/miui_HM6Pro_9.5.9_8d423fe112_9.0.zip",
  "9.5.30": "http://bigota.d.miui.com/9.5.30/miui_HM6Pro_9.5.30_855c057059_9.0.zip",
  "9.5.23": "http://bigota.d.miui.com/9.5.23/miui_HM6Pro_9.5.23_8a2d1b7633_9.0.zip",
  "9.5.16": "http://bigota.d.miui.com/9.5.16/miui_HM6Pro_9.5.16_3cce4ebf66_9.0.zip",
  "9.4.25": "http://bigota.d.miui.com/9.4.25/miui_HM6Pro_9.4.25_b7234c930e_9.0.zip",
  "9.4.18": "http://bigota.d.miui.com/9.4.18/miui_HM6Pro_9.4.18_d60707ca1c_9.0.zip",
  "9.4.12": "http://bigota.d.miui.com/9.4.12/miui_HM6Pro_9.4.12_87356b0004_9.0.zip",
  "9.3.7": "http://bigota.d.miui.com/9.3.7/miui_HM6Pro_9.3.7_9a7b231a99_9.0.zip",
  "9.3.28": "http://bigota.d.miui.com/9.3.28/miui_HM6Pro_9.3.28_69893e20a7_9.0.zip",
  "9.3.21": "http://bigota.d.miui.com/9.3.21/miui_HM6Pro_9.3.21_1a20d4c31c_9.0.zip",
  "9.3.14": "http://bigota.d.miui.com/9.3.14/miui_HM6Pro_9.3.14_11873ea73d_9.0.zip",
  "9.3.1": "http://bigota.d.miui.com/9.3.1/miui_HM6Pro_9.3.1_0a1c241c5c_9.0.zip",
  "9.2.21": "http://bigota.d.miui.com/9.2.21/miui_HM6Pro_9.2.21_af51878bff_9.0.zip",
  "9.2.15": "http://bigota.d.miui.com/9.2.15/miui_HM6Pro_9.2.15_968b9b16ea_9.0.zip",
  "9.1.26": "http://bigota.d.miui.com/9.1.26/miui_HM6Pro_9.1.26_ad95ac4349_9.0.zip",
  "9.1.24": "http://bigota.d.miui.com/9.1.24/miui_HM6Pro_9.1.24_14ca7ff398_8.1.zip",
  "9.1.17": "http://bigota.d.miui.com/9.1.17/miui_HM6Pro_9.1.17_800a61b669_8.1.zip",
  "9.1.10": "http://bigota.d.miui.com/9.1.10/miui_HM6Pro_9.1.10_3e84923be6_8.1.zip",
  "9.1.1": "http://bigota.d.miui.com/9.1.1/miui_HM6Pro_9.1.1_2d0a7305ca_8.1.zip",
  "8.9.6": "http://bigota.d.miui.com/8.9.6/miui_HM6Pro_8.9.6_f4f3706785_8.1.zip",
  "8.9.20": "http://bigota.d.miui.com/8.9.20/miui_HM6Pro_8.9.20_b580414638_8.1.zip",
  "8.9.13": "http://bigota.d.miui.com/8.9.13/miui_HM6Pro_8.9.13_4e8900c8a5_8.1.zip",
  "8.8.9": "http://bigota.d.miui.com/8.8.9/miui_HM6Pro_8.8.9_b357447bdb_8.1.zip",
  "8.8.30": "http://bigota.d.miui.com/8.8.30/miui_HM6Pro_8.8.30_4a02055908_8.1.zip",
  "8.8.3": "http://bigota.d.miui.com/8.8.3/miui_HM6Pro_8.8.3_8a603aad2d_8.1.zip",
  "8.8.23": "http://bigota.d.miui.com/8.8.23/miui_HM6Pro_8.8.23_76094ee4e1_8.1.zip",
  "8.8.16": "http://bigota.d.miui.com/8.8.16/miui_HM6Pro_8.8.16_3f35c1bb2f_8.1.zip",
  "8.7.26": "http://bigota.d.miui.com/8.7.26/miui_HM6Pro_8.7.26_898980b2cc_8.1.zip",
  "8.7.19": "http://bigota.d.miui.com/8.7.19/miui_HM6Pro_8.7.19_99d9cf89f0_8.1.zip",
  "8.7.12": "http://bigota.d.miui.com/8.7.12/miui_HM6Pro_8.7.12_ed48bd3b54_8.1.zip",
  "8.12.6": "http://bigota.d.miui.com/8.12.6/miui_HM6Pro_8.12.6_9c606777be_8.1.zip",
  "8.12.20": "http://bigota.d.miui.com/8.12.20/miui_HM6Pro_8.12.20_4ad1662679_8.1.zip",
  "8.12.13": "http://bigota.d.miui.com/8.12.13/miui_HM6Pro_8.12.13_eb4e2358dc_8.1.zip",
  "8.11.29": "http://bigota.d.miui.com/8.11.29/miui_HM6Pro_8.11.29_79de8c0c44_8.1.zip",
  "8.11.23": "http://bigota.d.miui.com/8.11.23/miui_HM6Pro_8.11.23_45db2f4c20_8.1.zip",
  "8.11.15": "http://bigota.d.miui.com/8.11.15/miui_HM6Pro_8.11.15_9a11df5104_8.1.zip",
  "8.11.1": "http://bigota.d.miui.com/8.11.1/miui_HM6Pro_8.11.1_7d74935eb4_8.1.zip",
  "8.10.25": "http://bigota.d.miui.com/8.10.25/miui_HM6Pro_8.10.25_b71329b380_8.1.zip",
  "8.10.18": "http://bigota.d.miui.com/8.10.18/miui_HM6Pro_8.10.18_bc30589d23_8.1.zip",
  "8.10.11": "http://bigota.d.miui.com/8.10.11/miui_HM6Pro_8.10.11_87a6611a24_8.1.zip"
 }
}